nevis/__init__.py
nevis/_bng.py
nevis/_interpolation.py
nevis/_nevis_version.py
nevis/_os_terrain_50.py
nevis/_plot.py
nevis/_util.py
nevis/_bin/hills.zip
nevis-0.1.0.dist-info/LICENSE.md
nevis-0.1.0.dist-info/METADATA
nevis-0.1.0.dist-info/WHEEL
nevis-0.1.0.dist-info/top_level.txt
nevis-0.1.0.dist-info/RECORD
