Metadata-Version: 2.1
Name: nevis
Version: 0.1.0
Summary: Presents the landscape of Great Britain as a testbed for optimisation and sampling methods.
Home-page: https://github.com/CardiacModelling/BenNevis
Author: The Where Is Ben Nevis team
Author-email: michael.clerx@nottingham.ac.uk
License: BSD 3-clause license
Project-URL: Bug Tracker, https://github.com/CardiacModelling/BenNevis/issues/
Project-URL: Documentation, https://nevis.readthedocs.io/
Project-URL: Source Code, https://github.com/CardiacModelling/BenNevis/
Classifier: Development Status :: 3 - Alpha
Classifier: Intended Audience :: Science/Research
Classifier: License :: OSI Approved :: BSD License
Classifier: Operating System :: OS Independent
Classifier: Programming Language :: Python :: 3
Classifier: Topic :: Scientific/Engineering
Classifier: Topic :: Scientific/Engineering :: Mathematics
Requires-Python: >=3.6
License-File: LICENSE.md
Requires-Dist: bnglonlat
Requires-Dist: matplotlib (>=1.5)
Requires-Dist: numpy
Requires-Dist: pykml
Requires-Dist: scipy
Requires-Dist: setuptools
Requires-Dist: zipfile-deflate64
Provides-Extra: dev
Requires-Dist: flake8 (>=3) ; extra == 'dev'
Requires-Dist: sphinx (!=1.7.3,>=1.5) ; extra == 'dev'
Provides-Extra: extras
Requires-Dist: convertbng ; extra == 'extras'
Requires-Dist: pillow ; extra == 'extras'
